cryptmoji/__init__.py
cryptmoji/cli.py
cryptmoji/data.py
cryptmoji/main.py
cryptmoji/version.py
cryptmoji-2.1.2.dist-info/entry_points.txt
cryptmoji-2.1.2.dist-info/LICENSE
cryptmoji-2.1.2.dist-info/METADATA
cryptmoji-2.1.2.dist-info/WHEEL
cryptmoji-2.1.2.dist-info/RECORD
